excel_helper/__init__.py
excel_helper/helper.py
excel_helper/init.rst
excel_helper/version.py
excel_modelling_helper-0.7.3.dist-info/METADATA
excel_modelling_helper-0.7.3.dist-info/RECORD
excel_modelling_helper-0.7.3.dist-info/WHEEL
excel_modelling_helper-0.7.3.dist-info/pbr.json
excel_modelling_helper-0.7.3.dist-info/top_level.txt
